vit_zoo/__init__.py
vit_zoo/model.py
vit_zoo/components/__init__.py
vit_zoo/components/backbone.py
vit_zoo/components/heads.py
vit_zoo/factory/__init__.py
vit_zoo/factory/builder.py
vit_zoo/factory/registry.py
vit_zoo/types/__init__.py
vit_zoo/types/interfaces.py
vit_zoo-0.1.4.dist-info/METADATA
vit_zoo-0.1.4.dist-info/WHEEL
vit_zoo-0.1.4.dist-info/top_level.txt
vit_zoo-0.1.4.dist-info/RECORD
