Metadata-Version: 2.4
Name: vit_zoo
Version: 0.1.4
Summary: Vision Transformers Zoo
Author-email: Jakub Binda <binkuba@gmail.com>
Maintainer-email: Jakub Binda <binkuba@gmail.com>
License: GPL-3.0
Project-URL: Source, https://github.com/jbindaAI/vit_zoo
Project-URL: Issues, https://github.com/jbindaAI/vit_zoo/issues
Project-URL: CI, https://github.com/jbindaAI/vit_zoo/actions
Project-URL: Changelog, https://github.com/jbindaAI/vit_zoo/releases
Project-URL: PyPI, https://pypi.org/project/vit-zoo/
Keywords: Vision Transformers
Classifier: License :: OSI Approved :: GNU General Public License v3 (GPLv3)
Classifier: Programming Language :: Python :: 3 :: Only
Classifier: Operating System :: OS Independent
Classifier: Development Status :: 4 - Beta
Classifier: Intended Audience :: Developers
Classifier: Intended Audience :: Science/Research
Classifier: Intended Audience :: Education
Classifier: Topic :: Scientific/Engineering
Requires-Python: >=3.9
Requires-Dist: torch
Requires-Dist: torchvision
Requires-Dist: transformers[torch]
Provides-Extra: dev
Requires-Dist: pytest; extra == "dev"
